umqtt.py
urequests.py
MicroWebSrv2/__init__.py
MicroWebSrv2/httpRequest.py
MicroWebSrv2/httpResponse.py
MicroWebSrv2/microWebSrv2.py
MicroWebSrv2/webRoute.py
MicroWebSrv2/libs/XAsyncSockets.py
MicroWebSrv2/libs/__init__.py
MicroWebSrv2/libs/urlUtils.py
MicroWebSrv2/mods/PyhtmlTemplate.py
MicroWebSrv2/mods/WebSockets.py
MicroWebSrv2/mods/__init__.py
cayennelpp/__init__.py
cayennelpp/lpp_data.py
cayennelpp/lpp_frame.py
cayennelpp/lpp_type.py
collections/__init__.py
collections/defaultdict.py
dotty_dict/__init__.py
dotty_dict/dotty_dict.py
dragino/Config.py
dragino/GPShandler.py
dragino/MAChandler.py
dragino/Strings.py
dragino/__init__.py
dragino/dragino.py
dragino/reset.py
dragino/LoRaWAN/AES_CMAC.py
dragino/LoRaWAN/DataPayload.py
dragino/LoRaWAN/Direction.py
dragino/LoRaWAN/FHDR.py
dragino/LoRaWAN/JoinAcceptPayload.py
dragino/LoRaWAN/JoinRequestPayload.py
dragino/LoRaWAN/MHDR.py
dragino/LoRaWAN/MacPayload.py
dragino/LoRaWAN/MalformedPacketException.py
dragino/LoRaWAN/PhyPayload.py
dragino/LoRaWAN/__init__.py
dragino/SX127x/LoRa.py
dragino/SX127x/LoRaArgumentParser.py
dragino/SX127x/__init__.py
dragino/SX127x/board_config.py
dragino/SX127x/constants.py
logging/__init__.py
logging/handlers.py
urllib/__init__.py
urllib/parse.py
vedirect/__init__.py
vedirect/vedirect.py
terkin_micropython_libraries-0.14.0.dist-info/METADATA
terkin_micropython_libraries-0.14.0.dist-info/WHEEL
terkin_micropython_libraries-0.14.0.dist-info/top_level.txt
terkin_micropython_libraries-0.14.0.dist-info/RECORD
